gitparse/__init__.py
gitparse/cli.py
gitparse/core/__init__.py
gitparse/core/async_repo_analyzer.py
gitparse/core/exceptions.py
gitparse/core/functions/__init__.py
gitparse/core/functions/dependencies.py
gitparse/core/functions/directory.py
gitparse/core/functions/file_content.py
gitparse/core/functions/file_tree.py
gitparse/core/functions/language_stats.py
gitparse/core/functions/readme.py
gitparse/core/functions/repository_info.py
gitparse/core/functions/statistics.py
gitparse/core/repository_analyzer.py
gitparse/parsers/__init__.py
gitparse/parsers/constants.py
gitparse/parsers/deps/__init__.py
gitparse/parsers/deps/base.py
gitparse/parsers/deps/nodejs.py
gitparse/parsers/deps/python.py
gitparse/schema/__init__.py
gitparse/schema/config.py
gitparse/utils/__init__.py
gitparse/utils/fs_utils.py
gitparse/vars/__init__.py
gitparse/vars/exclude_patterns.py
gitparse/vars/file_types.py
gitparse/vars/git_hosts.py
gitparse/vars/limits.py
gitparse-0.1.4.dist-info/entry_points.txt
gitparse-0.1.4.dist-info/METADATA
gitparse-0.1.4.dist-info/WHEEL
gitparse-0.1.4.dist-info/RECORD
