Metadata-Version: 2.3
Name: gitparse
Version: 0.1.4
Summary: A typed, modular Python library for structured repository parsing
License: MIT
Keywords: git,repository,parser,analysis,metadata
Author: Victor von Sohsten
Author-email: vondevelopment@gmail.com
Requires-Python: >=3.9
Classifier: Development Status :: 4 - Beta
Classifier: Intended Audience :: Developers
Classifier: License :: OSI Approved :: MIT License
Classifier: Programming Language :: Python :: 3
Classifier: Programming Language :: Python :: 3.9
Classifier: Programming Language :: Python :: 3.10
Classifier: Programming Language :: Python :: 3.11
Classifier: Topic :: Software Development :: Libraries :: Python Modules
Classifier: Topic :: Software Development :: Version Control :: Git
Requires-Dist: aiofiles (>=24.0.0,<25.0.0)
Requires-Dist: colorama (>=0.4.0,<0.5.0)
Requires-Dist: gitpython (>=3.1.0,<4.0.0)
Requires-Dist: packaging (>=23.0,<24.0)
Requires-Dist: pydantic (>=2.0.0,<3.0.0)
Requires-Dist: python-magic (>=0.4.0,<0.5.0)
Requires-Dist: rich (>=13.7.0,<14.0.0)
Requires-Dist: tomli (>=2.0.0,<3.0.0)
Requires-Dist: typing-extensions (>=4.0.0,<5.0.0)
Project-URL: Bug Tracker, https://github.com/von-development/gitparse/issues
Project-URL: Documentation, https://github.com/von-development/gitparse#readme
Project-URL: Homepage, https://github.com/von-development/gitparse
Project-URL: Repository, https://github.com/von-development/gitparse.git
